releaselogit.py
releaselogit-0.18.0.dist-info/LICENSE
releaselogit-0.18.0.dist-info/METADATA
releaselogit-0.18.0.dist-info/WHEEL
releaselogit-0.18.0.dist-info/RECORD
