Metadata-Version: 2.3
Name: ReleaseLogIt
Version: 0.18.0
Summary: Manage release notes for Python projects.
License: MIT
Author: Hendrik du Toit
Author-email: hendrik@brightedge.co.za
Requires-Python: >=3.10
Classifier: Development Status :: 4 - Beta
Classifier: Intended Audience :: Developers
Classifier: Intended Audience :: Information Technology
Classifier: Intended Audience :: System Administrators
Classifier: License :: OSI Approved :: MIT License
Classifier: Topic :: Software Development :: Libraries :: Python Modules
Classifier: Topic :: System :: Archiving :: Packaging
Classifier: Programming Language :: Python :: 3.10
Classifier: Programming Language :: Python :: 3.11
Classifier: Programming Language :: Python :: 3.12
Requires-Dist: configparserext (>=1.4.8,<2.0.0)
Requires-Dist: semverit (>=0.4.2,<0.5.0)
Requires-Dist: toml (>=0.10.2,<0.11.0)
Project-URL: Homepage, https://github.com/BrightEdgeeServices/ReleaseLogIt
Project-URL: Repository, https://github.com/BrightEdgeeServices/ReleaseLogIt.git
Project-URL: changelog, https://github.com/BrightEdgeeServices/ReleaseLogIt/blob/enhancement/master/ReleaseNotes.md
Project-URL: issues, https://github.com/BrightEdgeeServices/ReleaseLogIt/issues
